scopes/__init__.py
scopes/py.typed
block_scopes-0.2.3.dist-info/METADATA
block_scopes-0.2.3.dist-info/WHEEL
block_scopes-0.2.3.dist-info/licenses/LICENSE
block_scopes-0.2.3.dist-info/RECORD
