Metadata-Version: 2.1
Name: block-scopes
Version: 0.2.3
Summary: Block scopes in Python? Whaaaaaat?!
Project-URL: Documentation, https://github.com/cadojo/block-scopes#readme
Project-URL: Issues, https://github.com/cadojo/block-scopes/issues
Project-URL: Source, https://github.com/cadojo/block-scopes
Author-email: Joe Carpinelli <jdcarpinelli@gmail.com>
License-Expression: MIT
License-File: LICENSE
Keywords: cursed,hack,memory,scoping,variables
Classifier: Development Status :: 4 - Beta
Classifier: Programming Language :: Python
Classifier: Programming Language :: Python :: 3.8
Classifier: Programming Language :: Python :: 3.9
Classifier: Programming Language :: Python :: 3.10
Classifier: Programming Language :: Python :: 3.11
Classifier: Programming Language :: Python :: Implementation :: CPython
Classifier: Programming Language :: Python :: Implementation :: PyPy
Classifier: Typing :: Typed
Requires-Python: >=3.8
Requires-Dist: module-hygiene>=0.3.4
